secure_network/__init__.py
secure_network/authenticator.py
secure_network/network.py
secure_network-1.0.13.dist-info/METADATA
secure_network-1.0.13.dist-info/WHEEL
secure_network-1.0.13.dist-info/top_level.txt
secure_network-1.0.13.dist-info/RECORD
