Metadata-Version: 2.2
Name: secure_network
Version: 1.0.13
Summary: A secure networking extension with authentication, HMAC, and encryption.
Home-page: https://github.com/NeoZett/SecureNetwork
Author: Neo Zetterberg
Author-email: 20091103neo@gmail.com
Classifier: Programming Language :: Python :: 3
Classifier: License :: OSI Approved :: MIT License
Classifier: Operating System :: OS Independent
Requires-Python: >=3.7
Requires-Dist: cryptography
Requires-Dist: bcrypt
Requires-Dist: pyotp
Requires-Dist: requests
Dynamic: author
Dynamic: author-email
Dynamic: classifier
Dynamic: description
Dynamic: description-content-type
Dynamic: home-page
Dynamic: requires-dist
Dynamic: requires-python
Dynamic: summary
